pudb/__init__.py
pudb/__main__.py
pudb/_shtab.py
pudb/b.py
pudb/debugger.py
pudb/forked.py
pudb/ipython.py
pudb/lowlevel.py
pudb/remote.py
pudb/run.py
pudb/settings.py
pudb/shell.py
pudb/source_view.py
pudb/theme.py
pudb/ui_tools.py
pudb/var_view.py
pudb/test/__init__.py
pudb/test/test_lowlevel.py
pudb/test/test_make_canvas.py
pudb/test/test_run.py
pudb/test/test_settings.py
pudb/test/test_source_code_providers.py
pudb/test/test_var_view.py
pudb/themes/__init__.py
pudb/themes/agr_256.py
pudb/themes/classic.py
pudb/themes/dark_vim.py
pudb/themes/gray_light_256.py
pudb/themes/midnight.py
pudb/themes/mono.py
pudb/themes/monokai.py
pudb/themes/monokai_256.py
pudb/themes/nord_dark_256.py
pudb/themes/solarized.py
pudb/themes/utils.py
pudb/themes/vim.py
pudb-2025.1.5.dist-info/METADATA
pudb-2025.1.5.dist-info/WHEEL
pudb-2025.1.5.dist-info/entry_points.txt
pudb-2025.1.5.dist-info/licenses/LICENSE
pudb-2025.1.5.dist-info/RECORD
