Metadata-Version: 2.4
Name: pudb
Version: 2025.1.5
Summary: A full-screen, console-based Python debugger
Author-email: Andreas Kloeckner <inform@tiker.net>
License-Expression: MIT
License-File: LICENSE
Classifier: Development Status :: 4 - Beta
Classifier: Environment :: Console
Classifier: Environment :: Console :: Curses
Classifier: Intended Audience :: Developers
Classifier: Natural Language :: English
Classifier: Operating System :: POSIX
Classifier: Operating System :: Unix
Classifier: Programming Language :: Python
Classifier: Programming Language :: Python :: 3
Classifier: Topic :: Software Development
Classifier: Topic :: Software Development :: Debuggers
Classifier: Topic :: Software Development :: Quality Assurance
Classifier: Topic :: System :: Recovery Tools
Classifier: Topic :: System :: Software Distribution
Classifier: Topic :: Terminals
Classifier: Topic :: Utilities
Requires-Python: ~=3.8
Requires-Dist: jedi<1,>=0.18
Requires-Dist: packaging>=20.0
Requires-Dist: pygments>=2.19
Requires-Dist: typing-extensions>=4.13
Requires-Dist: urwid-readline
Requires-Dist: urwid>=2.4
Requires-Dist: urwid>=2.5.1
Provides-Extra: completion
Requires-Dist: shtab; extra == 'completion'
